sphinx_docstring_typing/__init__.py
sphinx_docstring_typing-0.0.4.dist-info/METADATA
sphinx_docstring_typing-0.0.4.dist-info/RECORD
sphinx_docstring_typing-0.0.4.dist-info/WHEEL
sphinx_docstring_typing-0.0.4.dist-info/top_level.txt
