Metadata-Version: 2.1
Name: sphinx-docstring-typing
Version: 0.0.4
Summary: Typing annotations in sphinx docstrings.
Home-page: UNKNOWN
Author: UNKNOWN
Author-email: UNKNOWN
License: Apache 2.0
Keywords: sphinx docstrings typing napoleon
Platform: UNKNOWN
Classifier: Programming Language :: Python :: 3
Classifier: Programming Language :: Python :: 3.4
Classifier: Programming Language :: Python :: 3.5
Classifier: Development Status :: 5 - Production/Stable
Classifier: Intended Audience :: Developers
Classifier: License :: OSI Approved :: Apache Software License
Classifier: Operating System :: POSIX
Classifier: Topic :: Internet :: WWW/HTTP
Requires-Dist: typing; python_version<"3.5"
